datasette_auth_github/__init__.py
datasette_auth_github/utils.py
datasette_auth_github/views.py
datasette_auth_github/templates/datasette_auth_github_error.html
datasette_auth_github-0.14.dist-info/licenses/LICENSE
datasette_auth_github-0.14.dist-info/METADATA
datasette_auth_github-0.14.dist-info/WHEEL
datasette_auth_github-0.14.dist-info/entry_points.txt
datasette_auth_github-0.14.dist-info/top_level.txt
datasette_auth_github-0.14.dist-info/RECORD
