Metadata-Version: 2.4
Name: datasette-auth-github
Version: 0.14
Summary: Datasette plugin and ASGI middleware that authenticates users against GitHub
Author: Simon Willison
License-Expression: Apache-2.0
Project-URL: Homepage, https://github.com/simonw/datasette-auth-github
Project-URL: Changelog, https://github.com/simonw/datasette-auth-github/releases
Project-URL: Issues, https://github.com/simonw/datasette-auth-github/issues
Requires-Python: >=3.10
License-File: LICENSE
Requires-Dist: datasette
Provides-Extra: test
Requires-Dist: pytest; extra == "test"
Requires-Dist: pytest-asyncio; extra == "test"
Requires-Dist: sqlite-utils; extra == "test"
Requires-Dist: pytest-httpx; extra == "test"
Dynamic: license-file
